mozart/__init__.py
mozart/dataconverter.py
mozart/model.py
mozart/dlls/Mozart.Common.dll
mozart/dlls/Mozart.Common.pdb
mozart/dlls/Mozart.Compression.dll
mozart/dlls/Mozart.Compression.pdb
mozart/dlls/Mozart.Data.Entity.dll
mozart/dlls/Mozart.Data.Entity.pdb
mozart/dlls/Mozart.Data.dll
mozart/dlls/Mozart.Data.pdb
mozart/dlls/Mozart.DataActions.dll
mozart/dlls/Mozart.DataActions.pdb
mozart/dlls/Mozart.Distributions.dll
mozart/dlls/Mozart.Distributions.pdb
mozart/dlls/Mozart.Remoting.dll
mozart/dlls/Mozart.Remoting.pdb
mozart/dlls/Mozart.Task.Framework.dll
mozart/dlls/Mozart.Task.Framework.pdb
mozart/dlls/Mozart.Task.Model.dll
mozart/dlls/Mozart.Task.Model.pdb
mozart/dlls/Mozart.XmlSerialization.dll
mozart/dlls/Mozart.XmlSerialization.pdb
mozartpy_test-0.0.1.dist-info/METADATA
mozartpy_test-0.0.1.dist-info/WHEEL
mozartpy_test-0.0.1.dist-info/top_level.txt
mozartpy_test-0.0.1.dist-info/RECORD
