Metadata-Version: 2.1
Name: mozartpy-test
Version: 0.0.1
Summary: Anaylize for Mozart Data
Home-page: UNKNOWN
Author: Brad Kang
Author-email: kundory@gmail.com
License: UNKNOWN
Platform: UNKNOWN
Classifier: Programming Language :: Python :: 3
Classifier: License :: OSI Approved :: MIT License
Classifier: Operating System :: OS Independent
Requires-Python: >=3.6
